pecc/__init__.py
pecc/_unexpected_alleles.py
pecc/data/A.csv
pecc/data/B.csv
pecc/data/C.csv
pecc/data/DP.csv
pecc/data/DQ.csv
pecc/data/DR.csv
pecc/data/ep_data.csv
pecc/epitope_comparison.py
pecc/epitope_comparison_aux.py
pecc/output_type.py
pecc-0.2.4.dist-info/WHEEL
pecc-0.2.4.dist-info/METADATA
pecc-0.2.4.dist-info/RECORD
