Metadata-Version: 2.1
Name: pecc
Version: 0.2.4
Summary: Python Epitopic Charge Calculator
Author: JasonMendoza2008
Author-email: lhotteromain@gmail.com
Requires-Python: >=3.10,<4.0
Classifier: Programming Language :: Python :: 3
Classifier: Programming Language :: Python :: 3.10
Classifier: Programming Language :: Python :: 3.11
Requires-Dist: openpyxl (>=3.0.10,<4.0.0)
Requires-Dist: pandas (>=1.5.1,<2.0.0)
